{
  "blogs": [
    {
      "author": "Rajan",
      "title": "New Features",
      "body": "<p>New edit</p>",
      "id": 2
    },
    {
      "title": "Issue",
      "body": "I typed everything in newline but text came in only one line in the blog",
      "author": "Rajan",
      "id": 3
    },
    {
      "title": "New feature",
      "body": "Like/comment",
      "author": "Manuj",
      "id": 4
    },
    {
      "title": "This is new Blog",
      "body": "<p>This is <strong>Bold </strong>text.</p>",
      "author": "Manuj",
      "id": 5
    },
    {
      "author": "Rajan",
      "title": "This is new Blog",
      "body": "<p>Ye kya ho gya</p>",
      "id": 6
    },
    {
      "title": "Hello",
      "body": "<p>World</p>",
      "author": "Manuj",
      "id": 7
    }
  ],
  "users": [
    {
      "name": "Rajan",
      "description": "My roll number is 1910990184",
      "id": 1
    },
    {
      "name": "Rajan",
      "description": "I am noob",
      "id": 2
    },
    {
      "name": "Manuj",
      "description": "Helo",
      "id": 3
    }
  ]
}